adeweb_docker_scripts/__init__.py
adeweb_docker_scripts/main.py
adeweb_docker_scripts-0.1.3.dist-info/entry_points.txt
adeweb_docker_scripts-0.1.3.dist-info/LICENSE
adeweb_docker_scripts-0.1.3.dist-info/WHEEL
adeweb_docker_scripts-0.1.3.dist-info/METADATA
adeweb_docker_scripts-0.1.3.dist-info/RECORD
